ip_subnet_trie/__init__.py
ip_subnet_trie/base.py
ip_subnet_trie/binary_trie_pb2.py
ip_subnet_trie/trie_ip_subnet.py
ip_subnet_trie/trie_serializers.py
ip_subnet_trie/utils.py
tests/__init__.py
tests/test_trie_ipv4_subnet.py
tests/test_trie_ipv6_subnet.py
IP_Subnet_Trie-1.0.dist-info/LICENSE.txt
IP_Subnet_Trie-1.0.dist-info/METADATA
IP_Subnet_Trie-1.0.dist-info/WHEEL
IP_Subnet_Trie-1.0.dist-info/top_level.txt
IP_Subnet_Trie-1.0.dist-info/RECORD
