Metadata-Version: 2.1
Name: IP-Subnet-Trie
Version: 1.0
Summary: An efficient data structure for handling a large number of IP addresses/subnets in a hierarchy.
Home-page: https://github.com/nguoinaodo/ip-subnet-trie
Author: Bui Hoang Luu
Author-email: luugu196@gmail.com
Classifier: License :: OSI Approved :: MIT License
Classifier: Programming Language :: Python :: 3.7
Classifier: Programming Language :: Python :: 3.8
Classifier: Programming Language :: Python :: 3.9
Classifier: Programming Language :: Python :: 3.10
License-File: LICENSE.txt
